DESCRIPTION.md
MANIFEST.in
setup.py
pygcrypt/__init__.py
pygcrypt/_gcrypt.py
pygcrypt/build_gcrypt.py
pygcrypt/build_gerror.py
pygcrypt/ciphers.py
pygcrypt/context.py
pygcrypt/ecurve.py
pygcrypt/errors.py
pygcrypt/hashcontext.py
pygcrypt/hmaccontext.py
pygcrypt/utils.py
pygcrypt.egg-info/PKG-INFO
pygcrypt.egg-info/SOURCES.txt
pygcrypt.egg-info/dependency_links.txt
pygcrypt.egg-info/requires.txt
pygcrypt.egg-info/top_level.txt
pygcrypt/gctypes/__init__.py
pygcrypt/gctypes/ec_point.py
pygcrypt/gctypes/key.py
pygcrypt/gctypes/mpi.py
pygcrypt/gctypes/sexpression.py
pygcrypt/test/__init__.py
pygcrypt/test/conftest.py
pygcrypt/test/test_ciphers.py
pygcrypt/test/test_ec_point.py
pygcrypt/test/test_ecurve.py
pygcrypt/test/test_hash.py
pygcrypt/test/test_hmac.py
pygcrypt/test/test_keys.py
pygcrypt/test/test_mpi.py
pygcrypt/test/test_sexpr.py
pygcrypt/test/test_utils.py