Metadata-Version: 1.1
Name: pygcrypt
Version: 1.0.0
Summary: libgcrypt in Python
Home-page: https://framagit.org/okhin/pygcrypt/
Author: okhin
Author-email: okhin@okhin.fr
License: GPLv3
Keywords: gpg crypto libgcrypt
Platform: UNKNOWN
Classifier: Development Status :: 4 - Beta
Classifier: Intended Audience :: Developers
Classifier: Topic :: Software Development :: Libraries :: Python Modules
Classifier: Topic :: Security :: Cryptography
Classifier: License :: OSI Approved :: GNU General Public License v3 (GPLv3)
Classifier: Programming Language :: Python :: 3
Classifier: Programming Language :: Python :: 3.2
Classifier: Programming Language :: Python :: 3.3
Classifier: Programming Language :: Python :: 3.4
